{
  "summary": {
    "total_amount": 28497544870197.0,
    "total_str": "28.5조",
    "theme_amount": 26021123329216.0,
    "theme_str": "26.0조",
    "theme_ratio": 91.3,
    "sector_count": 9,
    "theme_count": 14,
    "top60_count": 60
  },
  "sectors": [
    {
      "sector": "디스플레이/IT부품",
      "total_amount": 8804975818575.0,
      "total_str": "8.8조",
      "themes": [
        {
          "theme": "무선충전기술",
          "total_amount": 8311317560720.0,
          "total_str": "8.3조",
          "count": 2,
          "champion": {
            "ticker": "005930",
            "name": "삼성전자",
            "close": 232500,
            "change": 5.44,
            "amount": 7534835308220.0,
            "amount_str": "7.5조",
            "market": "KOSPI",
            "theme_name": "무선충전기술",
            "sector_name": "디스플레이/IT부품",
            "sector": {
              "theme": "무선충전기술",
              "sector": "디스플레이/IT부품"
            }
          },
          "stocks": [
            {
              "ticker": "009150",
              "name": "삼성전기",
              "close": 918000,
              "change": 10.34,
              "amount": 776482252500.0,
              "amount_str": "7764억",
              "market": "KOSPI",
              "theme_name": "무선충전기술",
              "sector_name": "디스플레이/IT부품",
              "sector": {
                "theme": "무선충전기술",
                "sector": "디스플레이/IT부품"
              }
            }
          ]
        },
        {
          "theme": "아이폰",
          "total_amount": 493658257855.0,
          "total_str": "4936억",
          "count": 2,
          "champion": {
            "ticker": "006400",
            "name": "삼성SDI",
            "close": 705000,
            "change": 1.44,
            "amount": 466135893500.0,
            "amount_str": "4661억",
            "market": "KOSPI",
            "theme_name": "아이폰",
            "sector_name": "디스플레이/IT부품",
            "sector": {
              "theme": "아이폰",
              "sector": "디스플레이/IT부품"
            }
          },
          "stocks": [
            {
              "ticker": "251370",
              "name": "와이엠티",
              "close": 20650,
              "change": 15.3,
              "amount": 27522364355.0,
              "amount_str": "275억",
              "market": "KOSDAQ",
              "theme_name": "아이폰",
              "sector_name": "디스플레이/IT부품",
              "sector": {
                "theme": "아이폰",
                "sector": "디스플레이/IT부품"
              }
            }
          ]
        }
      ]
    },
    {
      "sector": "AI/로봇",
      "total_amount": 8757768156250.0,
      "total_str": "8.8조",
      "themes": [
        {
          "theme": "온디바이스 AI",
          "total_amount": 8099065567750.0,
          "total_str": "8.1조",
          "count": 1,
          "champion": {
            "ticker": "000660",
            "name": "SK하이닉스",
            "close": 1447000,
            "change": 12.52,
            "amount": 8099065567750.0,
            "amount_str": "8.1조",
            "market": "KOSPI",
            "theme_name": "온디바이스 AI",
            "sector_name": "AI/로봇",
            "sector": {
              "theme": "온디바이스 AI",
              "sector": "AI/로봇"
            }
          },
          "stocks": []
        },
        {
          "theme": "UAM(도심항공모빌리티)",
          "total_amount": 658702588500.0,
          "total_str": "6587억",
          "count": 1,
          "champion": {
            "ticker": "012450",
            "name": "한화에어로스페이스",
            "close": 1465000,
            "change": 3.39,
            "amount": 658702588500.0,
            "amount_str": "6587억",
            "market": "KOSPI",
            "theme_name": "UAM(도심항공모빌리티)",
            "sector_name": "AI/로봇",
            "sector": {
              "theme": "UAM(도심항공모빌리티)",
              "sector": "AI/로봇"
            }
          },
          "stocks": []
        }
      ]
    },
    {
      "sector": "금융",
      "total_amount": 3138244700529.0,
      "total_str": "3.1조",
      "themes": [
        {
          "theme": "지주사",
          "total_amount": 1457591335686.0,
          "total_str": "1.5조",
          "count": 2,
          "champion": {
            "ticker": "402340",
            "name": "SK스퀘어",
            "close": 991000,
            "change": 17.84,
            "amount": 1417294936011.0,
            "amount_str": "1.4조",
            "market": "KOSPI",
            "theme_name": "지주사",
            "sector_name": "금융",
            "sector": {
              "theme": "지주사",
              "sector": "금융"
            }
          },
          "stocks": [
            {
              "ticker": "015860",
              "name": "일진홀딩스",
              "close": 13410,
              "change": 29.94,
              "amount": 40296399675.0,
              "amount_str": "402억",
              "market": "KOSDAQ",
              "theme_name": "지주사",
              "sector_name": "금융",
              "sector": {
                "theme": "지주사",
                "sector": "금융"
              }
            }
          ]
        },
        {
          "theme": "증권",
          "total_amount": 1003813891100.0,
          "total_str": "1.0조",
          "count": 2,
          "champion": {
            "ticker": "016360",
            "name": "삼성증권",
            "close": 137900,
            "change": 28.28,
            "amount": 558121362150.0,
            "amount_str": "5581억",
            "market": "KOSDAQ",
            "theme_name": "증권",
            "sector_name": "금융",
            "sector": {
              "theme": "증권",
              "sector": "금융"
            }
          },
          "stocks": [
            {
              "ticker": "006800",
              "name": "미래에셋증권",
              "close": 70300,
              "change": 8.49,
              "amount": 445692528950.0,
              "amount_str": "4456억",
              "market": "KOSPI",
              "theme_name": "증권",
              "sector_name": "금융",
              "sector": {
                "theme": "증권",
                "sector": "금융"
              }
            }
          ]
        },
        {
          "theme": "은행",
          "total_amount": 497551482493.0,
          "total_str": "4975억",
          "count": 3,
          "champion": {
            "ticker": "105560",
            "name": "KB금융",
            "close": 157800,
            "change": -1.68,
            "amount": 230728843600.0,
            "amount_str": "2307억",
            "market": "KOSPI",
            "theme_name": "은행",
            "sector_name": "금융",
            "sector": {
              "theme": "은행",
              "sector": "금융"
            }
          },
          "stocks": [
            {
              "ticker": "055550",
              "name": "신한지주",
              "close": 98000,
              "change": -1.9,
              "amount": 174778479593.0,
              "amount_str": "1747억",
              "market": "KOSPI",
              "theme_name": "은행",
              "sector_name": "금융",
              "sector": {
                "theme": "은행",
                "sector": "금융"
              }
            },
            {
              "ticker": "086790",
              "name": "하나금융지주",
              "close": 126600,
              "change": -1.02,
              "amount": 92044159300.0,
              "amount_str": "920억",
              "market": "KOSPI",
              "theme_name": "은행",
              "sector_name": "금융",
              "sector": {
                "theme": "은행",
                "sector": "금융"
              }
            }
          ]
        }
      ]
    },
    {
      "sector": "에너지/친환경",
      "total_amount": 1710965401835.0,
      "total_str": "1.7조",
      "themes": [
        {
          "theme": "LNG(액화천연가스)",
          "total_amount": 693190914000.0,
          "total_str": "6931억",
          "count": 2,
          "champion": {
            "ticker": "005490",
            "name": "POSCO홀딩스",
            "close": 502000,
            "change": 8.66,
            "amount": 542790614250.0,
            "amount_str": "5427억",
            "market": "KOSPI",
            "theme_name": "LNG(액화천연가스)",
            "sector_name": "에너지/친환경",
            "sector": {
              "theme": "LNG(액화천연가스)",
              "sector": "에너지/친환경"
            }
          },
          "stocks": [
            {
              "ticker": "034730",
              "name": "SK",
              "close": 475500,
              "change": 11.88,
              "amount": 150400299750.0,
              "amount_str": "1504억",
              "market": "KOSPI",
              "theme_name": "LNG(액화천연가스)",
              "sector_name": "에너지/친환경",
              "sector": {
                "theme": "LNG(액화천연가스)",
                "sector": "에너지/친환경"
              }
            }
          ]
        }
      ]
    },
    {
      "sector": "전기차/미래차",
      "total_amount": 1316739274700.0,
      "total_str": "1.3조",
      "themes": [
        {
          "theme": "자동차 대표주",
          "total_amount": 673211892250.0,
          "total_str": "6732억",
          "count": 3,
          "champion": {
            "ticker": "005380",
            "name": "현대차",
            "close": 539000,
            "change": 1.51,
            "amount": 461102938500.0,
            "amount_str": "4611억",
            "market": "KOSPI",
            "theme_name": "자동차 대표주",
            "sector_name": "전기차/미래차",
            "sector": {
              "theme": "자동차 대표주",
              "sector": "전기차/미래차"
            }
          },
          "stocks": [
            {
              "ticker": "000270",
              "name": "기아",
              "close": 154000,
              "change": 1.45,
              "amount": 121046283500.0,
              "amount_str": "1210억",
              "market": "KOSPI",
              "theme_name": "자동차 대표주",
              "sector_name": "전기차/미래차",
              "sector": {
                "theme": "자동차 대표주",
                "sector": "전기차/미래차"
              }
            },
            {
              "ticker": "012330",
              "name": "현대모비스",
              "close": 431500,
              "change": 1.53,
              "amount": 91062670250.0,
              "amount_str": "910억",
              "market": "KOSPI",
              "theme_name": "자동차 대표주",
              "sector_name": "전기차/미래차",
              "sector": {
                "theme": "자동차 대표주",
                "sector": "전기차/미래차"
              }
            }
          ]
        },
        {
          "theme": "전기차(충전소/충전기)",
          "total_amount": 643527382450.0,
          "total_str": "6435억",
          "count": 1,
          "champion": {
            "ticker": "006910",
            "name": "보성파워텍",
            "close": 14350,
            "change": 18.79,
            "amount": 643527382450.0,
            "amount_str": "6435억",
            "market": "KOSDAQ",
            "theme_name": "전기차(충전소/충전기)",
            "sector_name": "전기차/미래차",
            "sector": {
              "theme": "전기차(충전소/충전기)",
              "sector": "전기차/미래차"
            }
          },
          "stocks": []
        }
      ]
    },
    {
      "sector": "반도체",
      "total_amount": 1175700048750.0,
      "total_str": "1.2조",
      "themes": [
        {
          "theme": "시스템반도체",
          "total_amount": 665322176850.0,
          "total_str": "6653억",
          "count": 3,
          "champion": {
            "ticker": "042700",
            "name": "한미반도체",
            "close": 378000,
            "change": 2.72,
            "amount": 400885670500.0,
            "amount_str": "4008억",
            "market": "KOSPI",
            "theme_name": "시스템반도체",
            "sector_name": "반도체",
            "sector": {
              "theme": "시스템반도체",
              "sector": "반도체"
            }
          },
          "stocks": [
            {
              "ticker": "059120",
              "name": "아진엑스텍",
              "close": 11580,
              "change": 29.97,
              "amount": 151449499350.0,
              "amount_str": "1514억",
              "market": "KOSDAQ",
              "theme_name": "시스템반도체",
              "sector_name": "반도체",
              "sector": {
                "theme": "시스템반도체",
                "sector": "반도체"
              }
            },
            {
              "ticker": "254490",
              "name": "미래반도체",
              "close": 29250,
              "change": 25.27,
              "amount": 112987007000.0,
              "amount_str": "1129억",
              "market": "KOSDAQ",
              "theme_name": "시스템반도체",
              "sector_name": "반도체",
              "sector": {
                "theme": "시스템반도체",
                "sector": "반도체"
              }
            }
          ]
        }
      ]
    },
    {
      "sector": "조선/해운",
      "total_amount": 552535025860.0,
      "total_str": "5525억",
      "themes": [
        {
          "theme": "조선",
          "total_amount": 552535025860.0,
          "total_str": "5525억",
          "count": 3,
          "champion": {
            "ticker": "329180",
            "name": "HD현대중공업",
            "close": 680000,
            "change": -0.73,
            "amount": 293485124460.0,
            "amount_str": "2934억",
            "market": "KOSPI",
            "theme_name": "조선",
            "sector_name": "조선/해운",
            "sector": {
              "theme": "조선",
              "sector": "조선/해운"
            }
          },
          "stocks": [
            {
              "ticker": "042660",
              "name": "한화오션",
              "close": 133000,
              "change": 0.91,
              "amount": 201174360650.0,
              "amount_str": "2011억",
              "market": "KOSPI",
              "theme_name": "조선",
              "sector_name": "조선/해운",
              "sector": {
                "theme": "조선",
                "sector": "조선/해운"
              }
            },
            {
              "ticker": "009540",
              "name": "HD한국조선해양",
              "close": 469500,
              "change": 1.73,
              "amount": 57875540750.0,
              "amount_str": "578억",
              "market": "KOSPI",
              "theme_name": "조선",
              "sector_name": "조선/해운",
              "sector": {
                "theme": "조선",
                "sector": "조선/해운"
              }
            }
          ]
        }
      ]
    },
    {
      "sector": "바이오/제약/헬스케어",
      "total_amount": 290480181410.0,
      "total_str": "2904억",
      "themes": [
        {
          "theme": "바이오시밀러(복제 바이오의약품)",
          "total_amount": 257286970650.0,
          "total_str": "2572억",
          "count": 2,
          "champion": {
            "ticker": "207940",
            "name": "삼성바이오로직스",
            "close": 1485000,
            "change": 1.02,
            "amount": 134563092000.0,
            "amount_str": "1345억",
            "market": "KOSPI",
            "theme_name": "바이오시밀러(복제 바이오의약품)",
            "sector_name": "바이오/제약/헬스케어",
            "sector": {
              "theme": "바이오시밀러(복제 바이오의약품)",
              "sector": "바이오/제약/헬스케어"
            }
          },
          "stocks": [
            {
              "ticker": "068270",
              "name": "셀트리온",
              "close": 197800,
              "change": -1.35,
              "amount": 122723878650.0,
              "amount_str": "1227억",
              "market": "KOSPI",
              "theme_name": "바이오시밀러(복제 바이오의약품)",
              "sector_name": "바이오/제약/헬스케어",
              "sector": {
                "theme": "바이오시밀러(복제 바이오의약품)",
                "sector": "바이오/제약/헬스케어"
              }
            }
          ]
        }
      ]
    },
    {
      "sector": "IT/소프트웨어/플랫폼",
      "total_amount": 273714721307.0,
      "total_str": "2737억",
      "themes": [
        {
          "theme": "통신장비",
          "total_amount": 273714721307.0,
          "total_str": "2737억",
          "count": 5,
          "champion": {
            "ticker": "230240",
            "name": "에치에프알",
            "close": 36600,
            "change": 24.07,
            "amount": 84885525875.0,
            "amount_str": "848억",
            "market": "KOSDAQ",
            "theme_name": "통신장비",
            "sector_name": "IT/소프트웨어/플랫폼",
            "sector": {
              "theme": "통신장비",
              "sector": "IT/소프트웨어/플랫폼"
            }
          },
          "stocks": [
            {
              "ticker": "100590",
              "name": "머큐리",
              "close": 7410,
              "change": 19.52,
              "amount": 61453686035.0,
              "amount_str": "614억",
              "market": "KOSDAQ",
              "theme_name": "통신장비",
              "sector_name": "IT/소프트웨어/플랫폼",
              "sector": {
                "theme": "통신장비",
                "sector": "IT/소프트웨어/플랫폼"
              }
            },
            {
              "ticker": "033790",
              "name": "피노",
              "close": 16130,
              "change": 18.78,
              "amount": 54773368025.0,
              "amount_str": "547억",
              "market": "KOSDAQ",
              "theme_name": "통신장비",
              "sector_name": "IT/소프트웨어/플랫폼",
              "sector": {
                "theme": "통신장비",
                "sector": "IT/소프트웨어/플랫폼"
              }
            },
            {
              "ticker": "321370",
              "name": "센서뷰",
              "close": 3565,
              "change": 17.66,
              "amount": 51412355437.0,
              "amount_str": "514억",
              "market": "KOSDAQ",
              "theme_name": "통신장비",
              "sector_name": "IT/소프트웨어/플랫폼",
              "sector": {
                "theme": "통신장비",
                "sector": "IT/소프트웨어/플랫폼"
              }
            },
            {
              "ticker": "088280",
              "name": "쏘닉스",
              "close": 7640,
              "change": 6.56,
              "amount": 21189785935.0,
              "amount_str": "211억",
              "market": "KOSDAQ",
              "theme_name": "통신장비",
              "sector_name": "IT/소프트웨어/플랫폼",
              "sector": {
                "theme": "통신장비",
                "sector": "IT/소프트웨어/플랫폼"
              }
            }
          ]
        }
      ]
    }
  ],
  "date": "2026년 05월 05일",
  "generated_at": "15:32",
  "top60": [
    {
      "ticker": "000660",
      "name": "SK하이닉스",
      "close": 1447000,
      "change": 12.52,
      "amount": 8099065567750.0,
      "amount_str": "8.1조",
      "market": "KOSPI",
      "theme_name": "온디바이스 AI",
      "sector_name": "AI/로봇",
      "sector": {
        "theme": "온디바이스 AI",
        "sector": "AI/로봇"
      }
    },
    {
      "ticker": "005930",
      "name": "삼성전자",
      "close": 232500,
      "change": 5.44,
      "amount": 7534835308220.0,
      "amount_str": "7.5조",
      "market": "KOSPI",
      "theme_name": "무선충전기술",
      "sector_name": "디스플레이/IT부품",
      "sector": {
        "theme": "무선충전기술",
        "sector": "디스플레이/IT부품"
      }
    },
    {
      "ticker": "402340",
      "name": "SK스퀘어",
      "close": 991000,
      "change": 17.84,
      "amount": 1417294936011.0,
      "amount_str": "1.4조",
      "market": "KOSPI",
      "theme_name": "지주사",
      "sector_name": "금융",
      "sector": {
        "theme": "지주사",
        "sector": "금융"
      }
    },
    {
      "ticker": "009150",
      "name": "삼성전기",
      "close": 918000,
      "change": 10.34,
      "amount": 776482252500.0,
      "amount_str": "7764억",
      "market": "KOSPI",
      "theme_name": "무선충전기술",
      "sector_name": "디스플레이/IT부품",
      "sector": {
        "theme": "무선충전기술",
        "sector": "디스플레이/IT부품"
      }
    },
    {
      "ticker": "005935",
      "name": "삼성전자우",
      "close": 169600,
      "change": 7.14,
      "amount": 729745381350.0,
      "amount_str": "7297억",
      "market": "KOSPI",
      "theme_name": "기타",
      "sector_name": "기타",
      "sector": {
        "theme": "기타",
        "sector": "기타"
      }
    },
    {
      "ticker": "062040",
      "name": "산일전기",
      "close": 333500,
      "change": 25.38,
      "amount": 660463328500.0,
      "amount_str": "6604억",
      "market": "KOSDAQ",
      "theme_name": "기타",
      "sector_name": "기타",
      "sector": {
        "theme": "기타",
        "sector": "기타"
      }
    },
    {
      "ticker": "012450",
      "name": "한화에어로스페이스",
      "close": 1465000,
      "change": 3.39,
      "amount": 658702588500.0,
      "amount_str": "6587억",
      "market": "KOSPI",
      "theme_name": "UAM(도심항공모빌리티)",
      "sector_name": "AI/로봇",
      "sector": {
        "theme": "UAM(도심항공모빌리티)",
        "sector": "AI/로봇"
      }
    },
    {
      "ticker": "006910",
      "name": "보성파워텍",
      "close": 14350,
      "change": 18.79,
      "amount": 643527382450.0,
      "amount_str": "6435억",
      "market": "KOSDAQ",
      "theme_name": "전기차(충전소/충전기)",
      "sector_name": "전기차/미래차",
      "sector": {
        "theme": "전기차(충전소/충전기)",
        "sector": "전기차/미래차"
      }
    },
    {
      "ticker": "016360",
      "name": "삼성증권",
      "close": 137900,
      "change": 28.28,
      "amount": 558121362150.0,
      "amount_str": "5581억",
      "market": "KOSDAQ",
      "theme_name": "증권",
      "sector_name": "금융",
      "sector": {
        "theme": "증권",
        "sector": "금융"
      }
    },
    {
      "ticker": "005490",
      "name": "POSCO홀딩스",
      "close": 502000,
      "change": 8.66,
      "amount": 542790614250.0,
      "amount_str": "5427억",
      "market": "KOSPI",
      "theme_name": "LNG(액화천연가스)",
      "sector_name": "에너지/친환경",
      "sector": {
        "theme": "LNG(액화천연가스)",
        "sector": "에너지/친환경"
      }
    },
    {
      "ticker": "006400",
      "name": "삼성SDI",
      "close": 705000,
      "change": 1.44,
      "amount": 466135893500.0,
      "amount_str": "4661억",
      "market": "KOSPI",
      "theme_name": "아이폰",
      "sector_name": "디스플레이/IT부품",
      "sector": {
        "theme": "아이폰",
        "sector": "디스플레이/IT부품"
      }
    },
    {
      "ticker": "005380",
      "name": "현대차",
      "close": 539000,
      "change": 1.51,
      "amount": 461102938500.0,
      "amount_str": "4611억",
      "market": "KOSPI",
      "theme_name": "자동차 대표주",
      "sector_name": "전기차/미래차",
      "sector": {
        "theme": "자동차 대표주",
        "sector": "전기차/미래차"
      }
    },
    {
      "ticker": "006800",
      "name": "미래에셋증권",
      "close": 70300,
      "change": 8.49,
      "amount": 445692528950.0,
      "amount_str": "4456억",
      "market": "KOSPI",
      "theme_name": "증권",
      "sector_name": "금융",
      "sector": {
        "theme": "증권",
        "sector": "금융"
      }
    },
    {
      "ticker": "010120",
      "name": "LS ELECTRIC",
      "close": 294000,
      "change": 5.76,
      "amount": 432240344000.0,
      "amount_str": "4322억",
      "market": "KOSPI",
      "theme_name": "초전도체",
      "sector_name": "반도체",
      "sector": {
        "theme": "초전도체",
        "sector": "반도체"
      }
    },
    {
      "ticker": "034020",
      "name": "두산에너빌리티",
      "close": 127200,
      "change": 0.08,
      "amount": 408045473800.0,
      "amount_str": "4080억",
      "market": "KOSPI",
      "theme_name": "핵융합에너지",
      "sector_name": "에너지/친환경",
      "sector": {
        "theme": "핵융합에너지",
        "sector": "에너지/친환경"
      }
    },
    {
      "ticker": "042700",
      "name": "한미반도체",
      "close": 378000,
      "change": 2.72,
      "amount": 400885670500.0,
      "amount_str": "4008억",
      "market": "KOSPI",
      "theme_name": "시스템반도체",
      "sector_name": "반도체",
      "sector": {
        "theme": "시스템반도체",
        "sector": "반도체"
      }
    },
    {
      "ticker": "329180",
      "name": "HD현대중공업",
      "close": 680000,
      "change": -0.73,
      "amount": 293485124460.0,
      "amount_str": "2934억",
      "market": "KOSPI",
      "theme_name": "조선",
      "sector_name": "조선/해운",
      "sector": {
        "theme": "조선",
        "sector": "조선/해운"
      }
    },
    {
      "ticker": "298040",
      "name": "효성중공업",
      "close": 4228000,
      "change": 8.08,
      "amount": 281594335000.0,
      "amount_str": "2815억",
      "market": "KOSPI",
      "theme_name": "풍력에너지",
      "sector_name": "에너지/친환경",
      "sector": {
        "theme": "풍력에너지",
        "sector": "에너지/친환경"
      }
    },
    {
      "ticker": "267260",
      "name": "HD현대일렉트릭",
      "close": 1299000,
      "change": 3.75,
      "amount": 247808618500.0,
      "amount_str": "2478억",
      "market": "KOSPI",
      "theme_name": "전력설비",
      "sector_name": "에너지/친환경",
      "sector": {
        "theme": "전력설비",
        "sector": "에너지/친환경"
      }
    },
    {
      "ticker": "105560",
      "name": "KB금융",
      "close": 157800,
      "change": -1.68,
      "amount": 230728843600.0,
      "amount_str": "2307억",
      "market": "KOSPI",
      "theme_name": "은행",
      "sector_name": "금융",
      "sector": {
        "theme": "은행",
        "sector": "금융"
      }
    },
    {
      "ticker": "042660",
      "name": "한화오션",
      "close": 133000,
      "change": 0.91,
      "amount": 201174360650.0,
      "amount_str": "2011억",
      "market": "KOSPI",
      "theme_name": "조선",
      "sector_name": "조선/해운",
      "sector": {
        "theme": "조선",
        "sector": "조선/해운"
      }
    },
    {
      "ticker": "028260",
      "name": "삼성물산",
      "close": 320000,
      "change": 7.2,
      "amount": 200101110500.0,
      "amount_str": "2001억",
      "market": "KOSPI",
      "theme_name": "종합상사",
      "sector_name": "교육/기타서비스",
      "sector": {
        "theme": "종합상사",
        "sector": "교육/기타서비스"
      }
    },
    {
      "ticker": "373220",
      "name": "LG에너지솔루션",
      "close": 472000,
      "change": 2.5,
      "amount": 199992531500.0,
      "amount_str": "1999억",
      "market": "KOSPI",
      "theme_name": "2차전지(생산)",
      "sector_name": "2차전지/배터리",
      "sector": {
        "theme": "2차전지(생산)",
        "sector": "2차전지/배터리"
      }
    },
    {
      "ticker": "032830",
      "name": "삼성생명",
      "close": 265000,
      "change": 6.21,
      "amount": 179287991250.0,
      "amount_str": "1792억",
      "market": "KOSPI",
      "theme_name": "생명보험",
      "sector_name": "금융",
      "sector": {
        "theme": "생명보험",
        "sector": "금융"
      }
    },
    {
      "ticker": "055550",
      "name": "신한지주",
      "close": 98000,
      "change": -1.9,
      "amount": 174778479593.0,
      "amount_str": "1747억",
      "market": "KOSPI",
      "theme_name": "은행",
      "sector_name": "금융",
      "sector": {
        "theme": "은행",
        "sector": "금융"
      }
    },
    {
      "ticker": "035890",
      "name": "서희건설",
      "close": 3350,
      "change": 4.69,
      "amount": 174585068667.0,
      "amount_str": "1745억",
      "market": "KOSDAQ",
      "theme_name": "건설 중소형",
      "sector_name": "건설/인프라",
      "sector": {
        "theme": "건설 중소형",
        "sector": "건설/인프라"
      }
    },
    {
      "ticker": "059120",
      "name": "아진엑스텍",
      "close": 11580,
      "change": 29.97,
      "amount": 151449499350.0,
      "amount_str": "1514억",
      "market": "KOSDAQ",
      "theme_name": "시스템반도체",
      "sector_name": "반도체",
      "sector": {
        "theme": "시스템반도체",
        "sector": "반도체"
      }
    },
    {
      "ticker": "034730",
      "name": "SK",
      "close": 475500,
      "change": 11.88,
      "amount": 150400299750.0,
      "amount_str": "1504억",
      "market": "KOSPI",
      "theme_name": "LNG(액화천연가스)",
      "sector_name": "에너지/친환경",
      "sector": {
        "theme": "LNG(액화천연가스)",
        "sector": "에너지/친환경"
      }
    },
    {
      "ticker": "060370",
      "name": "LS마린솔루션",
      "close": 49550,
      "change": 29.88,
      "amount": 144510950875.0,
      "amount_str": "1445억",
      "market": "KOSDAQ",
      "theme_name": "해저터널(지하화/지하도로 등)",
      "sector_name": "건설/인프라",
      "sector": {
        "theme": "해저터널(지하화/지하도로 등)",
        "sector": "건설/인프라"
      }
    },
    {
      "ticker": "207940",
      "name": "삼성바이오로직스",
      "close": 1485000,
      "change": 1.02,
      "amount": 134563092000.0,
      "amount_str": "1345억",
      "market": "KOSPI",
      "theme_name": "바이오시밀러(복제 바이오의약품)",
      "sector_name": "바이오/제약/헬스케어",
      "sector": {
        "theme": "바이오시밀러(복제 바이오의약품)",
        "sector": "바이오/제약/헬스케어"
      }
    },
    {
      "ticker": "068270",
      "name": "셀트리온",
      "close": 197800,
      "change": -1.35,
      "amount": 122723878650.0,
      "amount_str": "1227억",
      "market": "KOSPI",
      "theme_name": "바이오시밀러(복제 바이오의약품)",
      "sector_name": "바이오/제약/헬스케어",
      "sector": {
        "theme": "바이오시밀러(복제 바이오의약품)",
        "sector": "바이오/제약/헬스케어"
      }
    },
    {
      "ticker": "000270",
      "name": "기아",
      "close": 154000,
      "change": 1.45,
      "amount": 121046283500.0,
      "amount_str": "1210억",
      "market": "KOSPI",
      "theme_name": "자동차 대표주",
      "sector_name": "전기차/미래차",
      "sector": {
        "theme": "자동차 대표주",
        "sector": "전기차/미래차"
      }
    },
    {
      "ticker": "254490",
      "name": "미래반도체",
      "close": 29250,
      "change": 25.27,
      "amount": 112987007000.0,
      "amount_str": "1129억",
      "market": "KOSDAQ",
      "theme_name": "시스템반도체",
      "sector_name": "반도체",
      "sector": {
        "theme": "시스템반도체",
        "sector": "반도체"
      }
    },
    {
      "ticker": "086790",
      "name": "하나금융지주",
      "close": 126600,
      "change": -1.02,
      "amount": 92044159300.0,
      "amount_str": "920억",
      "market": "KOSPI",
      "theme_name": "은행",
      "sector_name": "금융",
      "sector": {
        "theme": "은행",
        "sector": "금융"
      }
    },
    {
      "ticker": "012330",
      "name": "현대모비스",
      "close": 431500,
      "change": 1.53,
      "amount": 91062670250.0,
      "amount_str": "910억",
      "market": "KOSPI",
      "theme_name": "자동차 대표주",
      "sector_name": "전기차/미래차",
      "sector": {
        "theme": "자동차 대표주",
        "sector": "전기차/미래차"
      }
    },
    {
      "ticker": "230240",
      "name": "에치에프알",
      "close": 36600,
      "change": 24.07,
      "amount": 84885525875.0,
      "amount_str": "848억",
      "market": "KOSDAQ",
      "theme_name": "통신장비",
      "sector_name": "IT/소프트웨어/플랫폼",
      "sector": {
        "theme": "통신장비",
        "sector": "IT/소프트웨어/플랫폼"
      }
    },
    {
      "ticker": "475430",
      "name": "키스트론",
      "close": 6980,
      "change": 19.11,
      "amount": 80487477610.0,
      "amount_str": "804억",
      "market": "KOSDAQ",
      "theme_name": "기타",
      "sector_name": "기타",
      "sector": {
        "theme": "기타",
        "sector": "기타"
      }
    },
    {
      "ticker": "322310",
      "name": "오로스테크놀로지",
      "close": 44850,
      "change": 30.0,
      "amount": 78137527900.0,
      "amount_str": "781억",
      "market": "KOSDAQ",
      "theme_name": "HBM(고대역폭메모리)",
      "sector_name": "반도체",
      "sector": {
        "theme": "HBM(고대역폭메모리)",
        "sector": "반도체"
      }
    },
    {
      "ticker": "037030",
      "name": "파워넷",
      "close": 7440,
      "change": 29.84,
      "amount": 74958477710.0,
      "amount_str": "749억",
      "market": "KOSDAQ",
      "theme_name": "2차전지(LFP/리튬인산철)",
      "sector_name": "2차전지/배터리",
      "sector": {
        "theme": "2차전지(LFP/리튬인산철)",
        "sector": "2차전지/배터리"
      }
    },
    {
      "ticker": "000500",
      "name": "가온전선",
      "close": 288500,
      "change": 19.46,
      "amount": 62704551250.0,
      "amount_str": "627억",
      "market": "KOSDAQ",
      "theme_name": "전선",
      "sector_name": "에너지/친환경",
      "sector": {
        "theme": "전선",
        "sector": "에너지/친환경"
      }
    },
    {
      "ticker": "100590",
      "name": "머큐리",
      "close": 7410,
      "change": 19.52,
      "amount": 61453686035.0,
      "amount_str": "614억",
      "market": "KOSDAQ",
      "theme_name": "통신장비",
      "sector_name": "IT/소프트웨어/플랫폼",
      "sector": {
        "theme": "통신장비",
        "sector": "IT/소프트웨어/플랫폼"
      }
    },
    {
      "ticker": "009540",
      "name": "HD한국조선해양",
      "close": 469500,
      "change": 1.73,
      "amount": 57875540750.0,
      "amount_str": "578억",
      "market": "KOSPI",
      "theme_name": "조선",
      "sector_name": "조선/해운",
      "sector": {
        "theme": "조선",
        "sector": "조선/해운"
      }
    },
    {
      "ticker": "010130",
      "name": "고려아연",
      "close": 1629000,
      "change": 3.17,
      "amount": 56229507000.0,
      "amount_str": "562억",
      "market": "KOSPI",
      "theme_name": "환율하락 수혜",
      "sector_name": "기타",
      "sector": {
        "theme": "환율하락 수혜",
        "sector": "기타"
      }
    },
    {
      "ticker": "033790",
      "name": "피노",
      "close": 16130,
      "change": 18.78,
      "amount": 54773368025.0,
      "amount_str": "547억",
      "market": "KOSDAQ",
      "theme_name": "통신장비",
      "sector_name": "IT/소프트웨어/플랫폼",
      "sector": {
        "theme": "통신장비",
        "sector": "IT/소프트웨어/플랫폼"
      }
    },
    {
      "ticker": "321370",
      "name": "센서뷰",
      "close": 3565,
      "change": 17.66,
      "amount": 51412355437.0,
      "amount_str": "514억",
      "market": "KOSDAQ",
      "theme_name": "통신장비",
      "sector_name": "IT/소프트웨어/플랫폼",
      "sector": {
        "theme": "통신장비",
        "sector": "IT/소프트웨어/플랫폼"
      }
    },
    {
      "ticker": "015860",
      "name": "일진홀딩스",
      "close": 13410,
      "change": 29.94,
      "amount": 40296399675.0,
      "amount_str": "402억",
      "market": "KOSDAQ",
      "theme_name": "지주사",
      "sector_name": "금융",
      "sector": {
        "theme": "지주사",
        "sector": "금융"
      }
    },
    {
      "ticker": "006345",
      "name": "대원전선우",
      "close": 12920,
      "change": 29.98,
      "amount": 35316817655.0,
      "amount_str": "353억",
      "market": "KOSDAQ",
      "theme_name": "기타",
      "sector_name": "기타",
      "sector": {
        "theme": "기타",
        "sector": "기타"
      }
    },
    {
      "ticker": "021050",
      "name": "서원",
      "close": 1849,
      "change": 19.29,
      "amount": 33651968523.0,
      "amount_str": "336억",
      "market": "KOSDAQ",
      "theme_name": "비철금속",
      "sector_name": "철강/소재/화학",
      "sector": {
        "theme": "비철금속",
        "sector": "철강/소재/화학"
      }
    },
    {
      "ticker": "307180",
      "name": "아이엘",
      "close": 7730,
      "change": 21.92,
      "amount": 32124799245.0,
      "amount_str": "321억",
      "market": "KOSDAQ",
      "theme_name": "탈모 치료",
      "sector_name": "바이오/제약/헬스케어",
      "sector": {
        "theme": "탈모 치료",
        "sector": "바이오/제약/헬스케어"
      }
    },
    {
      "ticker": "251370",
      "name": "와이엠티",
      "close": 20650,
      "change": 15.3,
      "amount": 27522364355.0,
      "amount_str": "275억",
      "market": "KOSDAQ",
      "theme_name": "아이폰",
      "sector_name": "디스플레이/IT부품",
      "sector": {
        "theme": "아이폰",
        "sector": "디스플레이/IT부품"
      }
    },
    {
      "ticker": "479960",
      "name": "위너스일렉",
      "close": 13850,
      "change": 17.27,
      "amount": 25652140230.0,
      "amount_str": "256억",
      "market": "KOSDAQ",
      "theme_name": "기타",
      "sector_name": "기타",
      "sector": {
        "theme": "기타",
        "sector": "기타"
      }
    },
    {
      "ticker": "088280",
      "name": "쏘닉스",
      "close": 7640,
      "change": 6.56,
      "amount": 21189785935.0,
      "amount_str": "211억",
      "market": "KOSDAQ",
      "theme_name": "통신장비",
      "sector_name": "IT/소프트웨어/플랫폼",
      "sector": {
        "theme": "통신장비",
        "sector": "IT/소프트웨어/플랫폼"
      }
    },
    {
      "ticker": "092190",
      "name": "서울바이오시스",
      "close": 11230,
      "change": 29.98,
      "amount": 19457473350.0,
      "amount_str": "194억",
      "market": "KOSDAQ",
      "theme_name": "2020 상반기 신규상장",
      "sector_name": "신규상장",
      "sector": {
        "theme": "2020 상반기 신규상장",
        "sector": "신규상장"
      }
    },
    {
      "ticker": "044990",
      "name": "에이치엔에스하이텍",
      "close": 20000,
      "change": 22.7,
      "amount": 18145164355.0,
      "amount_str": "181억",
      "market": "KOSDAQ",
      "theme_name": "기타",
      "sector_name": "기타",
      "sector": {
        "theme": "기타",
        "sector": "기타"
      }
    },
    {
      "ticker": "189860",
      "name": "서전기전",
      "close": 8900,
      "change": 29.93,
      "amount": 17621509285.0,
      "amount_str": "176억",
      "market": "KOSDAQ",
      "theme_name": "스마트그리드(지능형전력망)",
      "sector_name": "에너지/친환경",
      "sector": {
        "theme": "스마트그리드(지능형전력망)",
        "sector": "에너지/친환경"
      }
    },
    {
      "ticker": "262260",
      "name": "에이프로",
      "close": 10990,
      "change": 27.35,
      "amount": 11217298435.0,
      "amount_str": "112억",
      "market": "KOSDAQ",
      "theme_name": "2020 하반기 신규상장",
      "sector_name": "신규상장",
      "sector": {
        "theme": "2020 하반기 신규상장",
        "sector": "신규상장"
      }
    },
    {
      "ticker": "121890",
      "name": "에스디시스템",
      "close": 2325,
      "change": 21.47,
      "amount": 7058484772.0,
      "amount_str": "70억",
      "market": "KOSDAQ",
      "theme_name": "기타",
      "sector_name": "기타",
      "sector": {
        "theme": "기타",
        "sector": "기타"
      }
    },
    {
      "ticker": "309930",
      "name": "조이웍스앤코",
      "close": 2210,
      "change": 19.98,
      "amount": 2529566089.0,
      "amount_str": "25억",
      "market": "KOSDAQ",
      "theme_name": "리모델링/인테리어",
      "sector_name": "건설/인프라",
      "sector": {
        "theme": "리모델링/인테리어",
        "sector": "건설/인프라"
      }
    },
    {
      "ticker": "058450",
      "name": "한주에이알티",
      "close": 5450,
      "change": 29.92,
      "amount": 2318793860.0,
      "amount_str": "23억",
      "market": "KOSDAQ",
      "theme_name": "기타",
      "sector_name": "기타",
      "sector": {
        "theme": "기타",
        "sector": "기타"
      }
    },
    {
      "ticker": "079190",
      "name": "케스피온",
      "close": 858,
      "change": 30.0,
      "amount": 1068411515.0,
      "amount_str": "10억",
      "market": "KOSDAQ",
      "theme_name": "엠폭스(원숭이두창)",
      "sector_name": "바이오/제약/헬스케어",
      "sector": {
        "theme": "엠폭스(원숭이두창)",
        "sector": "바이오/제약/헬스케어"
      }
    }
  ]
}